fastapi_di/__init__.py
fastapi_di/_client.py
fastapi_di/_injector.py
fastapi_di/_provide.py
fastapi_di/app.py
fastapi_di/env_fields.py
fastapi_di/py.typed
fastapi_di/testing.py
fastapi_magic_di-0.0.1a3.dist-info/LICENSE
fastapi_magic_di-0.0.1a3.dist-info/METADATA
fastapi_magic_di-0.0.1a3.dist-info/WHEEL
fastapi_magic_di-0.0.1a3.dist-info/RECORD
