Metadata-Version: 2.1
Name: fastapi-magic-di
Version: 0.0.1a3
Summary: Dependency Injector for FastAPI that makes your life easier
License: MIT
Author: Nikita Zavadin
Author-email: zavadin142@gmail.com
Requires-Python: >=3.9
Classifier: License :: OSI Approved :: MIT License
Classifier: Programming Language :: Python :: 3
Classifier: Programming Language :: Python :: 3.9
Classifier: Programming Language :: Python :: 3.10
Classifier: Programming Language :: Python :: 3.11
Requires-Dist: fastapi
